csvdiffgpt/__init__.py
csvdiffgpt/cli.py
csvdiffgpt/cleaners/__init__.py
csvdiffgpt/cleaners/base.py
csvdiffgpt/cleaners/helpers.py
csvdiffgpt/cleaners/high_cardinality.py
csvdiffgpt/cleaners/inconsistent_values.py
csvdiffgpt/cleaners/missing_values.py
csvdiffgpt/cleaners/outliers.py
csvdiffgpt/cleaners/type_issues.py
csvdiffgpt/core/__init__.py
csvdiffgpt/core/preprocessor.py
csvdiffgpt/core/utils.py
csvdiffgpt/data_models/__init__.py
csvdiffgpt/data_models/base.py
csvdiffgpt/data_models/mermaid_adapter.py
csvdiffgpt/data_models/python_adapter.py
csvdiffgpt/data_models/sql_adapter.py
csvdiffgpt/executor/__init__.py
csvdiffgpt/llm/__init__.py
csvdiffgpt/llm/base.py
csvdiffgpt/llm/gemini.py
csvdiffgpt/llm/openai.py
csvdiffgpt/restructure_analyzers/__init__.py
csvdiffgpt/restructure_analyzers/base.py
csvdiffgpt/restructure_analyzers/helpers.py
csvdiffgpt/restructure_analyzers/normalization_analyzer.py
csvdiffgpt/restructure_analyzers/redundancy_analyzer.py
csvdiffgpt/restructure_analyzers/relationship_analyzer.py
csvdiffgpt/restructure_analyzers/type_consistency_analyzer.py
csvdiffgpt/tasks/__init__.py
csvdiffgpt/tasks/clean.py
csvdiffgpt/tasks/compare.py
csvdiffgpt/tasks/explain_code.py
csvdiffgpt/tasks/generate_tests.py
csvdiffgpt/tasks/restructure.py
csvdiffgpt/tasks/summarize.py
csvdiffgpt/tasks/validate.py
csvdiffgpt/test_frameworks/__init__.py
csvdiffgpt/test_frameworks/base.py
csvdiffgpt/test_frameworks/dbt_adapter.py
csvdiffgpt/test_frameworks/framework_helpers.py
csvdiffgpt/test_frameworks/great_expectations_adapter.py
csvdiffgpt/test_frameworks/pytest_adapter.py
csvdiffgpt/test_generators/__init__.py
csvdiffgpt/test_generators/base.py
csvdiffgpt/test_generators/quality_tests.py
csvdiffgpt/test_generators/relationship_tests.py
csvdiffgpt/test_generators/schema_tests.py
csvdiffgpt/test_generators/value_tests.py
csvdiffgpt-0.1.4.dist-info/licenses/LICENSE
csvdiffgpt-0.1.4.dist-info/METADATA
csvdiffgpt-0.1.4.dist-info/WHEEL
csvdiffgpt-0.1.4.dist-info/entry_points.txt
csvdiffgpt-0.1.4.dist-info/top_level.txt
csvdiffgpt-0.1.4.dist-info/RECORD
