Metadata-Version: 2.4
Name: csvdiffgpt
Version: 0.1.4
Summary: A package for analyzing CSV files using LLMs
Home-page: https://github.com/SohamMane812/csvdiffgpt
Author: Soham Mane
Author-email: Soham Mane <sohammane01@gmail.com>
License-Expression: Apache-2.0
Project-URL: Homepage, https://github.com/SohamMane812/csvdiffgpt
Project-URL: Bug Tracker, https://github.com/SohamMane812/csvdiffgpt/issues
Classifier: Programming Language :: Python :: 3.9
Classifier: Programming Language :: Python :: 3.10
Classifier: Programming Language :: Python :: 3.11
Classifier: Operating System :: OS Independent
Requires-Python: >=3.9
License-File: LICENSE
Requires-Dist: pandas>=1.3.0
Requires-Dist: numpy>=1.20.0
Requires-Dist: pyyaml>=6.0
Provides-Extra: openai
Requires-Dist: openai>=1.0.0; extra == "openai"
Provides-Extra: gemini
Requires-Dist: google-generativeai>=0.8.5; extra == "gemini"
Provides-Extra: claude
Requires-Dist: anthropic>=0.5.0; extra == "claude"
Provides-Extra: dev
Requires-Dist: pytest>=6.0.0; extra == "dev"
Requires-Dist: black>=21.5b2; extra == "dev"
Requires-Dist: isort>=5.9.1; extra == "dev"
Requires-Dist: mypy>=0.812; extra == "dev"
Requires-Dist: types-PyYAML; extra == "dev"
Provides-Extra: all
Requires-Dist: openai>=1.0.0; extra == "all"
Requires-Dist: google-generativeai>=0.8.5; extra == "all"
Requires-Dist: anthropic>=0.5.0; extra == "all"
Dynamic: author
Dynamic: home-page
Dynamic: license-file
Dynamic: requires-python
